BUILDER_ADDON_PCA/.credentials.json
BUILDER_ADDON_PCA/__init__.py
BUILDER_ADDON_PCA/__main__.py
BUILDER_ADDON_PCA/addon.json
BUILDER_ADDON_PCA/_dev_tools/__init__.py
BUILDER_ADDON_PCA/_dev_tools/utils.py
BUILDER_ADDON_PCA/_dev_tools/addon_tasks/__init__.py
BUILDER_ADDON_PCA/_dev_tools/addon_tasks/add_on_manager_session.py
BUILDER_ADDON_PCA/_dev_tools/addon_tasks/bootstrap.py
BUILDER_ADDON_PCA/_dev_tools/addon_tasks/build.py
BUILDER_ADDON_PCA/_dev_tools/addon_tasks/deploy.py
BUILDER_ADDON_PCA/_dev_tools/addon_tasks/element_protocol.py
BUILDER_ADDON_PCA/_dev_tools/addon_tasks/logs.py
BUILDER_ADDON_PCA/_dev_tools/addon_tasks/package.py
BUILDER_ADDON_PCA/_dev_tools/addon_tasks/testing.py
BUILDER_ADDON_PCA/_dev_tools/addon_tasks/utils.py
BUILDER_ADDON_PCA/_dev_tools/addon_tasks/watch.py
BUILDER_ADDON_PCA/_dev_tools/defaults/__init__.py
BUILDER_ADDON_PCA/_dev_tools/defaults/data_lab_project/__init__.py
BUILDER_ADDON_PCA/_dev_tools/defaults/data_lab_project/element.py
BUILDER_ADDON_PCA/_dev_tools/defaults/formula_package/__init__.py
BUILDER_ADDON_PCA/_dev_tools/defaults/formula_package/element.py
BUILDER_ADDON_PCA/_dev_tools/defaults/plugin/__init__.py
BUILDER_ADDON_PCA/_dev_tools/defaults/plugin/element.py
BUILDER_ADDON_PCA/_dev_tools/tests/__init__.py
BUILDER_ADDON_PCA/_dev_tools/tests/test_utils.py
BUILDER_ADDON_PCA/dist/com.seeq.pca-0.0.1.addon
BUILDER_ADDON_PCA/dist/com.seeq.pca-0.0.1.addonmeta
BUILDER_ADDON_PCA/pca-addon-tool/Principal Component Analysis.ipynb
BUILDER_ADDON_PCA-0.0.8.data/data/BUILDER_ADDON_PCA/.credentials.json
BUILDER_ADDON_PCA-0.0.8.data/data/BUILDER_ADDON_PCA/Principal Component Analysis.ipynb
BUILDER_ADDON_PCA-0.0.8.data/data/BUILDER_ADDON_PCA/addon.json
BUILDER_ADDON_PCA-0.0.8.data/data/BUILDER_ADDON_PCA/dist/com.seeq.pca-0.0.1.addon
BUILDER_ADDON_PCA-0.0.8.data/data/BUILDER_ADDON_PCA/dist/com.seeq.pca-0.0.1.addonmeta
BUILDER_ADDON_PCA-0.0.8.dist-info/LICENSE
BUILDER_ADDON_PCA-0.0.8.dist-info/METADATA
BUILDER_ADDON_PCA-0.0.8.dist-info/WHEEL
BUILDER_ADDON_PCA-0.0.8.dist-info/top_level.txt
BUILDER_ADDON_PCA-0.0.8.dist-info/RECORD
