Metadata-Version: 2.1
Name: BUILDER_ADDON_PCA
Version: 0.0.8
Summary: package for installation of PCA Addon on Seeq
Author: e-matica
Author-email: software@e-matica.it
License: EULA Agreement
Classifier: Programming Language :: Python :: 3
Classifier: Operating System :: OS Independent
Requires-Python: >=3.6
License-File: LICENSE
Requires-Dist: seeq
Requires-Dist: seeq-spy
Requires-Dist: requests
Requires-Dist: watchfiles
Requires-Dist: beautifulsoup4
Requires-Dist: lxml
